Main.py
LiveCricketScoreNotifications-1.0.dist-info/LICENSE
LiveCricketScoreNotifications-1.0.dist-info/METADATA
LiveCricketScoreNotifications-1.0.dist-info/WHEEL
LiveCricketScoreNotifications-1.0.dist-info/top_level.txt
LiveCricketScoreNotifications-1.0.dist-info/RECORD
