Metadata-Version: 2.1
Name: LiveCricketScoreNotifications
Version: 1.0
Summary: Live Cricket Scores Notifications 
Home-page: UNKNOWN
Author: Vamil Gandhi
Author-email: vamilg@gmail.com
License: MIT
Platform: UNKNOWN
